numi/__init__.py
numi/handle_input.py
numi/main.py
numi/utils.py
numi-0.0.13.dist-info/LICENSE
numi-0.0.13.dist-info/METADATA
numi-0.0.13.dist-info/WHEEL
numi-0.0.13.dist-info/top_level.txt
numi-0.0.13.dist-info/RECORD
