Metadata-Version: 2.1
Name: numi
Version: 0.0.13
Summary: A package that expands Icelandic numbers to their corresponding written form
Home-page: https://gitlab.com/tiro-is/h10/numi
Author: David Erik Mollberg
Author-email: tiro@tiro.is
Project-URL: Bug Tracker, https://gitlab.com/tiro-is/h10/numi/issues
Classifier: Programming Language :: Python :: 3
Classifier: License :: OSI Approved :: MIT License
Classifier: Operating System :: OS Independent
Requires-Python: >=3.6
License-File: LICENSE
Provides-Extra: testing
Requires-Dist: pytest (>=6.0) ; extra == 'testing'
Requires-Dist: pytest-cov (>=2.0) ; extra == 'testing'
Requires-Dist: mypy (>=0.910) ; extra == 'testing'
Requires-Dist: flake8 (>=3.9) ; extra == 'testing'
Requires-Dist: tox (>=3.24) ; extra == 'testing'
